README.md
setup.cfg
setup.py
txredisapi.py
txredisapi3.egg-info/PKG-INFO
txredisapi3.egg-info/SOURCES.txt
txredisapi3.egg-info/dependency_links.txt
txredisapi3.egg-info/requires.txt
txredisapi3.egg-info/top_level.txt